{
    "p2kwiet2125006231309_btnWatchPop_onClick_seq0": {
        "id": "p2kwiet2125006231309_btnWatchPop_onClick_seq0",
        "type": "ACTION_SEQUENCE",
        "params": [{
            "name": "eventobject",
            "value": "eventobject"
        }],
        "language": "js",
        "actions": [{
            "id": "expression_onClick_607902125006233307",
            "type": "ADD_SNIPPET",
            "codeSnippet": "watchStopped.dismiss();\n "
        }, {
            "id": "navigation_onClick_450752125006235508",
            "type": "NAVIGATE_TO_FORM",
            "formId": "frmOptions",
            "formKUID": "p2kwiet2125006231263",
            "mappings": {},
            "mappingsOrder": [],
            "parentId": "",
            "enableMappingEditor": true
        }]
    }
}